{
    "img_shape": [
        2480,
        2200,
        3
    ],
    "texts": [
        {
            "id": 0,
            "content": "11 :20",
            "keyboard": false,
            "column_min": 44,
            "row_min": 18,
            "column_max": 113,
            "row_max": 45,
            "width": 69,
            "height": 27
        },
        {
            "id": 29,
            "content": "\u25cf\u25cf\u25cf",
            "keyboard": false,
            "column_min": 2050,
            "row_min": 415,
            "column_max": 2058,
            "row_max": 458,
            "width": 8,
            "height": 43
        },
        {
            "id": 1,
            "content": "Search your phone and more",
            "keyboard": false,
            "column_min": 119,
            "row_min": 418,
            "column_max": 790,
            "row_max": 466,
            "width": 671,
            "height": 48
        },
        {
            "id": 8,
            "content": "19",
            "keyboard": false,
            "column_min": 671,
            "row_min": 662,
            "column_max": 706,
            "row_max": 687,
            "width": 35,
            "height": 25
        },
        {
            "id": 2,
            "content": "Booking",
            "keyboard": false,
            "column_min": 232,
            "row_min": 664,
            "column_max": 329,
            "row_max": 689,
            "width": 97,
            "height": 25
        },
        {
            "id": 9,
            "content": "Calendar",
            "keyboard": false,
            "column_min": 627,
            "row_min": 777,
            "column_max": 754,
            "row_max": 802,
            "width": 127,
            "height": 25
        },
        {
            "id": 20,
            "content": "Chrome",
            "keyboard": false,
            "column_min": 1453,
            "row_min": 778,
            "column_max": 1564,
            "row_max": 802,
            "width": 111,
            "height": 24
        },
        {
            "id": 24,
            "content": "Clock",
            "keyboard": false,
            "column_min": 1878,
            "row_min": 778,
            "column_max": 1958,
            "row_max": 802,
            "width": 80,
            "height": 24
        },
        {
            "id": 3,
            "content": "Booking.com",
            "keyboard": false,
            "column_min": 189,
            "row_min": 779,
            "column_max": 371,
            "row_max": 807,
            "width": 182,
            "height": 28
        },
        {
            "id": 16,
            "content": "Camera",
            "keyboard": false,
            "column_min": 1045,
            "row_min": 780,
            "column_max": 1152,
            "row_max": 802,
            "width": 107,
            "height": 22
        },
        {
            "id": 25,
            "content": "G",
            "keyboard": false,
            "column_min": 1873,
            "row_min": 997,
            "column_max": 1965,
            "row_max": 1090,
            "width": 92,
            "height": 93
        },
        {
            "id": 10,
            "content": "A",
            "keyboard": false,
            "column_min": 645,
            "row_min": 1004,
            "column_max": 729,
            "row_max": 1080,
            "width": 84,
            "height": 76
        },
        {
            "id": 17,
            "content": "Files",
            "keyboard": false,
            "column_min": 1065,
            "row_min": 1145,
            "column_max": 1133,
            "row_max": 1172,
            "width": 68,
            "height": 27
        },
        {
            "id": 26,
            "content": "Google",
            "keyboard": false,
            "column_min": 1867,
            "row_min": 1145,
            "column_max": 1966,
            "row_max": 1176,
            "width": 99,
            "height": 31
        },
        {
            "id": 21,
            "content": "Gmail",
            "keyboard": false,
            "column_min": 1468,
            "row_min": 1146,
            "column_max": 1548,
            "row_max": 1172,
            "width": 80,
            "height": 26
        },
        {
            "id": 11,
            "content": "Drive",
            "keyboard": false,
            "column_min": 655,
            "row_min": 1147,
            "column_max": 727,
            "row_max": 1171,
            "width": 72,
            "height": 24
        },
        {
            "id": 4,
            "content": "Contacts",
            "keyboard": false,
            "column_min": 218,
            "row_min": 1148,
            "column_max": 344,
            "row_max": 1171,
            "width": 126,
            "height": 23
        },
        {
            "id": 12,
            "content": "110",
            "keyboard": false,
            "column_min": 662,
            "row_min": 1391,
            "column_max": 718,
            "row_max": 1443,
            "width": 56,
            "height": 52
        },
        {
            "id": 27,
            "content": "Play Store",
            "keyboard": false,
            "column_min": 1847,
            "row_min": 1514,
            "column_max": 1987,
            "row_max": 1545,
            "width": 140,
            "height": 31
        },
        {
            "id": 18,
            "content": "Phone",
            "keyboard": false,
            "column_min": 1055,
            "row_min": 1515,
            "column_max": 1144,
            "row_max": 1538,
            "width": 89,
            "height": 23
        },
        {
            "id": 13,
            "content": "Messages",
            "keyboard": false,
            "column_min": 616,
            "row_min": 1516,
            "column_max": 762,
            "row_max": 1544,
            "width": 146,
            "height": 28
        },
        {
            "id": 22,
            "content": "Photos",
            "keyboard": false,
            "column_min": 1459,
            "row_min": 1516,
            "column_max": 1557,
            "row_max": 1539,
            "width": 98,
            "height": 23
        },
        {
            "id": 5,
            "content": "Maps",
            "keyboard": false,
            "column_min": 242,
            "row_min": 1517,
            "column_max": 319,
            "row_max": 1545,
            "width": 77,
            "height": 28
        },
        {
            "id": 6,
            "content": "10",
            "keyboard": false,
            "column_min": 235,
            "row_min": 1752,
            "column_max": 315,
            "row_max": 1810,
            "width": 80,
            "height": 58
        },
        {
            "id": 14,
            "content": "TO",
            "keyboard": false,
            "column_min": 664,
            "row_min": 1796,
            "column_max": 723,
            "row_max": 1818,
            "width": 59,
            "height": 22
        },
        {
            "id": 23,
            "content": "YouTube",
            "keyboard": false,
            "column_min": 1445,
            "row_min": 1884,
            "column_max": 1568,
            "row_max": 1909,
            "width": 123,
            "height": 25
        },
        {
            "id": 28,
            "content": "YT Music",
            "keyboard": false,
            "column_min": 1850,
            "row_min": 1884,
            "column_max": 1984,
            "row_max": 1910,
            "width": 134,
            "height": 26
        },
        {
            "id": 7,
            "content": "Settings",
            "keyboard": false,
            "column_min": 223,
            "row_min": 1885,
            "column_max": 339,
            "row_max": 1914,
            "width": 116,
            "height": 29
        },
        {
            "id": 15,
            "content": "TMoble",
            "keyboard": false,
            "column_min": 637,
            "row_min": 1886,
            "column_max": 743,
            "row_max": 1908,
            "width": 106,
            "height": 22
        },
        {
            "id": 19,
            "content": "WebView Browser Tester",
            "keyboard": false,
            "column_min": 920,
            "row_min": 1886,
            "column_max": 1277,
            "row_max": 1909,
            "width": 357,
            "height": 23
        }
    ]
}